README.txt
binarySearch.py
setup.py
binSearchParash.egg-info/PKG-INFO
binSearchParash.egg-info/SOURCES.txt
binSearchParash.egg-info/dependency_links.txt
binSearchParash.egg-info/top_level.txt