Metadata-Version: 1.0
Name: binSearchParash
Version: 1.0
Summary: Intiser's Search Tools
Home-page: UNKNOWN
Author: Intiser Rajoan Parash
Author-email: irparash@gmail.com
License: UNKNOWN
Platform: UNKNOWN
